LICENSE
MANIFEST.in
README.md
quicktest.py
settings_test.py
setup.py
django_facebook_photos.egg-info/PKG-INFO
django_facebook_photos.egg-info/SOURCES.txt
django_facebook_photos.egg-info/dependency_links.txt
django_facebook_photos.egg-info/not-zip-safe
django_facebook_photos.egg-info/requires.txt
django_facebook_photos.egg-info/top_level.txt
facebook_photos/__init__.py
facebook_photos/__init__.pyc
facebook_photos/admin.py
facebook_photos/admin.pyc
facebook_photos/factories.py
facebook_photos/factories.pyc
facebook_photos/models.py
facebook_photos/models.pyc
facebook_photos/tests.py
facebook_photos/tests.pyc
facebook_photos/sql/album.postgresql_psycopg2.sql
facebook_photos/sql/photo.postgresql_psycopg2.sql